paddlepalm/__init__.py
paddlepalm/_downloader.py
paddlepalm/downloader.py
paddlepalm/multihead_trainer.py
paddlepalm/trainer.py
paddlepalm/backbone/__init__.py
paddlepalm/backbone/base_backbone.py
paddlepalm/backbone/bert.py
paddlepalm/backbone/ernie.py
paddlepalm/backbone/utils/__init__.py
paddlepalm/backbone/utils/transformer.py
paddlepalm/distribute/__init__.py
paddlepalm/distribute/reader.py
paddlepalm/head/__init__.py
paddlepalm/head/base_head.py
paddlepalm/head/cls.py
paddlepalm/head/match.py
paddlepalm/head/mlm.py
paddlepalm/head/mrc.py
paddlepalm/head/ner.py
paddlepalm/lr_sched/__init__.py
paddlepalm/lr_sched/base_schedualer.py
paddlepalm/lr_sched/slanted_triangular_schedualer.py
paddlepalm/lr_sched/warmup_schedualer.py
paddlepalm/optimizer/__init__.py
paddlepalm/optimizer/adam.py
paddlepalm/optimizer/base_optimizer.py
paddlepalm/reader/__init__.py
paddlepalm/reader/base_reader.py
paddlepalm/reader/cls.py
paddlepalm/reader/match.py
paddlepalm/reader/mlm.py
paddlepalm/reader/mrc.py
paddlepalm/reader/seq_label.py
paddlepalm/reader/utils/__init__.py
paddlepalm/reader/utils/batching4bert.py
paddlepalm/reader/utils/batching4ernie.py
paddlepalm/reader/utils/mlm_batching.py
paddlepalm/reader/utils/mrqa_helper.py
paddlepalm/reader/utils/reader4ernie.py
paddlepalm/tokenizer/__init__.py
paddlepalm/tokenizer/bert_tokenizer.py
paddlepalm/tokenizer/ernie_tokenizer.py
paddlepalm/utils/__init__.py
paddlepalm/utils/basic_helper.py
paddlepalm/utils/config_helper.py
paddlepalm/utils/plot_helper.py
paddlepalm/utils/print_helper.py
paddlepalm/utils/reader_helper.py
paddlepalm/utils/saver.py
paddlepalm/utils/textprocess_helper.py
paddlepalm-2.0.2.dist-info/METADATA
paddlepalm-2.0.2.dist-info/WHEEL
paddlepalm-2.0.2.dist-info/top_level.txt
paddlepalm-2.0.2.dist-info/RECORD
